{
    "odata.metadata": "$metadata#Collection(Edm.ComplexType)",
    "value": [
        {
            "PurchaseDeliveryNotes": {
                "DocEntry": 8,
                "DocNum": 1000008,
                "CreationDate": "2024-11-15",
                "CardCode": "VL-0002",
                "CardName": "Common Project Trading DMCC",
                "DocCurrency": "USD",
                "DocRate": 130.44,
                "NumAtCard": "Reebok SS24-KEN- J01",
                "Reference1": "1000008",
                "Comments": "Based On Purchase Orders 1000004.",
                "JournalMemo": "Goods Receipt PO - VL-0002"
            },
            "PurchaseDeliveryNotes/DocumentLines": {
                "ItemCode": "07/100074837/5-",
                "ItemDescription": "ENERGEN LUX",
                "ShipDate": "2024-09-01",
                "Quantity": 3.0,
                "Price": 18.95,
                "PriceAfterVAT": 18.95,
                "Currency": "USD",
                "WarehouseCode": "KEN\\JU01",
                "Rate": 130.44,
                "BarCode": "1200143200360",
                "GrossPrice": 18.95,
                "GrossTotal": 7415.51,
                "U_RRP": 0.0,
                "U_Article": null,
                "U_JumiaSKU": null,
                "U_FOC": "No",
                "UnitsOfMeasurment": 1.0
            }
        },
        {
            "PurchaseDeliveryNotes": {
                "DocEntry": 8,
                "DocNum": 1000008,
                "CreationDate": "2024-11-15",
                "CardCode": "VL-0002",
                "CardName": "Common Project Trading DMCC",
                "DocCurrency": "USD",
                "DocRate": 130.44,
                "NumAtCard": "Reebok SS24-KEN- J01",
                "Reference1": "1000008",
                "Comments": "Based On Purchase Orders 1000004.",
                "JournalMemo": "Goods Receipt PO - VL-0002"
            },
            "PurchaseDeliveryNotes/DocumentLines": {
                "ItemCode": "07/100074837/6",
                "ItemDescription": "ENERGEN LUX",
                "ShipDate": "2024-09-01",
                "Quantity": 3.0,
                "Price": 18.95,
                "PriceAfterVAT": 18.95,
                "Currency": "USD",
                "WarehouseCode": "KEN\\JU01",
                "Rate": 130.44,
                "BarCode": "1200143200384",
                "GrossPrice": 18.95,
                "GrossTotal": 7415.51,
                "U_RRP": 0.0,
                "U_Article": null,
                "U_JumiaSKU": null,
                "U_FOC": "No",
                "UnitsOfMeasurment": 1.0
            }
        },
        {
            "PurchaseDeliveryNotes": {
                "DocEntry": 8,
                "DocNum": 1000008,
                "CreationDate": "2024-11-15",
                "CardCode": "VL-0002",
                "CardName": "Common Project Trading DMCC",
                "DocCurrency": "USD",
                "DocRate": 130.44,
                "NumAtCard": "Reebok SS24-KEN- J01",
                "Reference1": "1000008",
                "Comments": "Based On Purchase Orders 1000004.",
                "JournalMemo": "Goods Receipt PO - VL-0002"
            },
            "PurchaseDeliveryNotes/DocumentLines": {
                "ItemCode": "07/100074837/6",
                "ItemDescription": "ENERGEN LUX",
                "ShipDate": "2024-09-01",
                "Quantity": 4.0,
                "Price": 18.95,
                "PriceAfterVAT": 18.95,
                "Currency": "USD",
                "WarehouseCode": "KEN\\JU01",
                "Rate": 130.44,
                "BarCode": "1200143200384",
                "GrossPrice": 18.95,
                "GrossTotal": 9887.35,
                "U_RRP": 0.0,
                "U_Article": null,
                "U_JumiaSKU": null,
                "U_FOC": "No",
                "UnitsOfMeasurment": 1.0
            }
        },
        {
            "PurchaseDeliveryNotes": {
                "DocEntry": 8,
                "DocNum": 1000008,
                "CreationDate": "2024-11-15",
                "CardCode": "VL-0002",
                "CardName": "Common Project Trading DMCC",
                "DocCurrency": "USD",
                "DocRate": 130.44,
                "NumAtCard": "Reebok SS24-KEN- J01",
                "Reference1": "1000008",
                "Comments": "Based On Purchase Orders 1000004.",
                "JournalMemo": "Goods Receipt PO - VL-0002"
            },
            "PurchaseDeliveryNotes/DocumentLines": {
                "ItemCode": "07/100074837/6-",
                "ItemDescription": "ENERGEN LUX",
                "ShipDate": "2024-09-01",
                "Quantity": 3.0,
                "Price": 18.95,
                "PriceAfterVAT": 18.95,
                "Currency": "USD",
                "WarehouseCode": "KEN\\JU01",
                "Rate": 130.44,
                "BarCode": "1200143200407",
                "GrossPrice": 18.95,
                "GrossTotal": 7415.51,
                "U_RRP": 0.0,
                "U_Article": null,
                "U_JumiaSKU": null,
                "U_FOC": "No",
                "UnitsOfMeasurment": 1.0
            }
        },
        {
            "PurchaseDeliveryNotes": {
                "DocEntry": 8,
                "DocNum": 1000008,
                "CreationDate": "2024-11-15",
                "CardCode": "VL-0002",
                "CardName": "Common Project Trading DMCC",
                "DocCurrency": "USD",
                "DocRate": 130.44,
                "NumAtCard": "Reebok SS24-KEN- J01",
                "Reference1": "1000008",
                "Comments": "Based On Purchase Orders 1000004.",
                "JournalMemo": "Goods Receipt PO - VL-0002"
            },
            "PurchaseDeliveryNotes/DocumentLines": {
                "ItemCode": "07/100074837/7",
                "ItemDescription": "ENERGEN LUX",
                "ShipDate": "2024-09-01",
                "Quantity": 2.0,
                "Price": 18.95,
                "PriceAfterVAT": 18.95,
                "Currency": "USD",
                "WarehouseCode": "KEN\\JU01",
                "Rate": 130.44,
                "BarCode": "1200143200421",
                "GrossPrice": 18.95,
                "GrossTotal": 4943.68,
                "U_RRP": 0.0,
                "U_Article": null,
                "U_JumiaSKU": null,
                "U_FOC": "No",
                "UnitsOfMeasurment": 1.0
            }
        },
        {
            "PurchaseDeliveryNotes": {
                "DocEntry": 8,
                "DocNum": 1000008,
                "CreationDate": "2024-11-15",
                "CardCode": "VL-0002",
                "CardName": "Common Project Trading DMCC",
                "DocCurrency": "USD",
                "DocRate": 130.44,
                "NumAtCard": "Reebok SS24-KEN- J01",
                "Reference1": "1000008",
                "Comments": "Based On Purchase Orders 1000004.",
                "JournalMemo": "Goods Receipt PO - VL-0002"
            },
            "PurchaseDeliveryNotes/DocumentLines": {
                "ItemCode": "07/100074845/3-",
                "ItemDescription": "REEBOK COURT RETRO",
                "ShipDate": "2024-09-01",
                "Quantity": 3.0,
                "Price": 18.22,
                "PriceAfterVAT": 18.22,
                "Currency": "USD",
                "WarehouseCode": "KEN\\JU01",
                "Rate": 130.44,
                "BarCode": "1200143202517",
                "GrossPrice": 18.22,
                "GrossTotal": 7129.85,
                "U_RRP": 0.0,
                "U_Article": null,
                "U_JumiaSKU": null,
                "U_FOC": "No",
                "UnitsOfMeasurment": 1.0
            }
        },
        {
            "PurchaseDeliveryNotes": {
                "DocEntry": 8,
                "DocNum": 1000008,
                "CreationDate": "2024-11-15",
                "CardCode": "VL-0002",
                "CardName": "Common Project Trading DMCC",
                "DocCurrency": "USD",
                "DocRate": 130.44,
                "NumAtCard": "Reebok SS24-KEN- J01",
                "Reference1": "1000008",
                "Comments": "Based On Purchase Orders 1000004.",
                "JournalMemo": "Goods Receipt PO - VL-0002"
            },
            "PurchaseDeliveryNotes/DocumentLines": {
                "ItemCode": "07/100074845/4",
                "ItemDescription": "REEBOK COURT RETRO",
                "ShipDate": "2024-09-01",
                "Quantity": 5.0,
                "Price": 18.22,
                "PriceAfterVAT": 18.22,
                "Currency": "USD",
                "WarehouseCode": "KEN\\JU01",
                "Rate": 130.44,
                "BarCode": "1200143202531",
                "GrossPrice": 18.22,
                "GrossTotal": 11883.08,
                "U_RRP": 0.0,
                "U_Article": null,
                "U_JumiaSKU": null,
                "U_FOC": "No",
                "UnitsOfMeasurment": 1.0
            }
        },
        {
            "PurchaseDeliveryNotes": {
                "DocEntry": 8,
                "DocNum": 1000008,
                "CreationDate": "2024-11-15",
                "CardCode": "VL-0002",
                "CardName": "Common Project Trading DMCC",
                "DocCurrency": "USD",
                "DocRate": 130.44,
                "NumAtCard": "Reebok SS24-KEN- J01",
                "Reference1": "1000008",
                "Comments": "Based On Purchase Orders 1000004.",
                "JournalMemo": "Goods Receipt PO - VL-0002"
            },
            "PurchaseDeliveryNotes/DocumentLines": {
                "ItemCode": "07/100074845/4",
                "ItemDescription": "REEBOK COURT RETRO",
                "ShipDate": "2024-09-01",
                "Quantity": 2.0,
                "Price": 18.22,
                "PriceAfterVAT": 18.22,
                "Currency": "USD",
                "WarehouseCode": "KEN\\JU01",
                "Rate": 130.44,
                "BarCode": "1200143202531",
                "GrossPrice": 18.22,
                "GrossTotal": 4753.23,
                "U_RRP": 0.0,
                "U_Article": null,
                "U_JumiaSKU": null,
                "U_FOC": "No",
                "UnitsOfMeasurment": 1.0
            }
        },
        {
            "PurchaseDeliveryNotes": {
                "DocEntry": 8,
                "DocNum": 1000008,
                "CreationDate": "2024-11-15",
                "CardCode": "VL-0002",
                "CardName": "Common Project Trading DMCC",
                "DocCurrency": "USD",
                "DocRate": 130.44,
                "NumAtCard": "Reebok SS24-KEN- J01",
                "Reference1": "1000008",
                "Comments": "Based On Purchase Orders 1000004.",
                "JournalMemo": "Goods Receipt PO - VL-0002"
            },
            "PurchaseDeliveryNotes/DocumentLines": {
                "ItemCode": "07/100074845/4-",
                "ItemDescription": "REEBOK COURT RETRO",
                "ShipDate": "2024-09-01",
                "Quantity": 1.0,
                "Price": 18.22,
                "PriceAfterVAT": 18.22,
                "Currency": "USD",
                "WarehouseCode": "KEN\\JU01",
                "Rate": 130.44,
                "BarCode": "1200143202555",
                "GrossPrice": 18.22,
                "GrossTotal": 2376.62,
                "U_RRP": 0.0,
                "U_Article": null,
                "U_JumiaSKU": null,
                "U_FOC": "No",
                "UnitsOfMeasurment": 1.0
            }
        },
        {
            "PurchaseDeliveryNotes": {
                "DocEntry": 8,
                "DocNum": 1000008,
                "CreationDate": "2024-11-15",
                "CardCode": "VL-0002",
                "CardName": "Common Project Trading DMCC",
                "DocCurrency": "USD",
                "DocRate": 130.44,
                "NumAtCard": "Reebok SS24-KEN- J01",
                "Reference1": "1000008",
                "Comments": "Based On Purchase Orders 1000004.",
                "JournalMemo": "Goods Receipt PO - VL-0002"
            },
            "PurchaseDeliveryNotes/DocumentLines": {
                "ItemCode": "07/100074845/4-",
                "ItemDescription": "REEBOK COURT RETRO",
                "ShipDate": "2024-09-01",
                "Quantity": 8.0,
                "Price": 18.22,
                "PriceAfterVAT": 18.22,
                "Currency": "USD",
                "WarehouseCode": "KEN\\JU01",
                "Rate": 130.44,
                "BarCode": "1200143202555",
                "GrossPrice": 18.22,
                "GrossTotal": 19012.93,
                "U_RRP": 0.0,
                "U_Article": null,
                "U_JumiaSKU": null,
                "U_FOC": "No",
                "UnitsOfMeasurment": 1.0
            }
        },
        {
            "PurchaseDeliveryNotes": {
                "DocEntry": 8,
                "DocNum": 1000008,
                "CreationDate": "2024-11-15",
                "CardCode": "VL-0002",
                "CardName": "Common Project Trading DMCC",
                "DocCurrency": "USD",
                "DocRate": 130.44,
                "NumAtCard": "Reebok SS24-KEN- J01",
                "Reference1": "1000008",
                "Comments": "Based On Purchase Orders 1000004.",
                "JournalMemo": "Goods Receipt PO - VL-0002"
            },
            "PurchaseDeliveryNotes/DocumentLines": {
                "ItemCode": "07/100074845/5",
                "ItemDescription": "REEBOK COURT RETRO",
                "ShipDate": "2024-09-01",
                "Quantity": 10.0,
                "Price": 18.22,
                "PriceAfterVAT": 18.22,
                "Currency": "USD",
                "WarehouseCode": "KEN\\JU01",
                "Rate": 130.44,
                "BarCode": "1200143202579",
                "GrossPrice": 18.22,
                "GrossTotal": 23766.17,
                "U_RRP": 0.0,
                "U_Article": null,
                "U_JumiaSKU": null,
                "U_FOC": "No",
                "UnitsOfMeasurment": 1.0
            }
        },
        {
            "PurchaseDeliveryNotes": {
                "DocEntry": 8,
                "DocNum": 1000008,
                "CreationDate": "2024-11-15",
                "CardCode": "VL-0002",
                "CardName": "Common Project Trading DMCC",
                "DocCurrency": "USD",
                "DocRate": 130.44,
                "NumAtCard": "Reebok SS24-KEN- J01",
                "Reference1": "1000008",
                "Comments": "Based On Purchase Orders 1000004.",
                "JournalMemo": "Goods Receipt PO - VL-0002"
            },
            "PurchaseDeliveryNotes/DocumentLines": {
                "ItemCode": "07/100074845/5",
                "ItemDescription": "REEBOK COURT RETRO",
                "ShipDate": "2024-09-01",
                "Quantity": 8.0,
                "Price": 18.22,
                "PriceAfterVAT": 18.22,
                "Currency": "USD",
                "WarehouseCode": "KEN\\JU01",
                "Rate": 130.44,
                "BarCode": "1200143202579",
                "GrossPrice": 18.22,
                "GrossTotal": 19012.93,
                "U_RRP": 0.0,
                "U_Article": null,
                "U_JumiaSKU": null,
                "U_FOC": "No",
                "UnitsOfMeasurment": 1.0
            }
        },
        {
            "PurchaseDeliveryNotes": {
                "DocEntry": 8,
                "DocNum": 1000008,
                "CreationDate": "2024-11-15",
                "CardCode": "VL-0002",
                "CardName": "Common Project Trading DMCC",
                "DocCurrency": "USD",
                "DocRate": 130.44,
                "NumAtCard": "Reebok SS24-KEN- J01",
                "Reference1": "1000008",
                "Comments": "Based On Purchase Orders 1000004.",
                "JournalMemo": "Goods Receipt PO - VL-0002"
            },
            "PurchaseDeliveryNotes/DocumentLines": {
                "ItemCode": "07/100074845/5-",
                "ItemDescription": "REEBOK COURT RETRO",
                "ShipDate": "2024-09-01",
                "Quantity": 4.0,
                "Price": 18.22,
                "PriceAfterVAT": 18.22,
                "Currency": "USD",
                "WarehouseCode": "KEN\\JU01",
                "Rate": 130.44,
                "BarCode": "1200143202593",
                "GrossPrice": 18.22,
                "GrossTotal": 9506.47,
                "U_RRP": 0.0,
                "U_Article": null,
                "U_JumiaSKU": null,
                "U_FOC": "No",
                "UnitsOfMeasurment": 1.0
            }
        },
        {
            "PurchaseDeliveryNotes": {
                "DocEntry": 8,
                "DocNum": 1000008,
                "CreationDate": "2024-11-15",
                "CardCode": "VL-0002",
                "CardName": "Common Project Trading DMCC",
                "DocCurrency": "USD",
                "DocRate": 130.44,
                "NumAtCard": "Reebok SS24-KEN- J01",
                "Reference1": "1000008",
                "Comments": "Based On Purchase Orders 1000004.",
                "JournalMemo": "Goods Receipt PO - VL-0002"
            },
            "PurchaseDeliveryNotes/DocumentLines": {
                "ItemCode": "07/100074845/5-",
                "ItemDescription": "REEBOK COURT RETRO",
                "ShipDate": "2024-09-01",
                "Quantity": 5.0,
                "Price": 18.22,
                "PriceAfterVAT": 18.22,
                "Currency": "USD",
                "WarehouseCode": "KEN\\JU01",
                "Rate": 130.44,
                "BarCode": "1200143202593",
                "GrossPrice": 18.22,
                "GrossTotal": 11883.08,
                "U_RRP": 0.0,
                "U_Article": null,
                "U_JumiaSKU": null,
                "U_FOC": "No",
                "UnitsOfMeasurment": 1.0
            }
        },
        {
            "PurchaseDeliveryNotes": {
                "DocEntry": 8,
                "DocNum": 1000008,
                "CreationDate": "2024-11-15",
                "CardCode": "VL-0002",
                "CardName": "Common Project Trading DMCC",
                "DocCurrency": "USD",
                "DocRate": 130.44,
                "NumAtCard": "Reebok SS24-KEN- J01",
                "Reference1": "1000008",
                "Comments": "Based On Purchase Orders 1000004.",
                "JournalMemo": "Goods Receipt PO - VL-0002"
            },
            "PurchaseDeliveryNotes/DocumentLines": {
                "ItemCode": "07/100074845/6",
                "ItemDescription": "REEBOK COURT RETRO",
                "ShipDate": "2024-09-01",
                "Quantity": 9.0,
                "Price": 18.22,
                "PriceAfterVAT": 18.22,
                "Currency": "USD",
                "WarehouseCode": "KEN\\JU01",
                "Rate": 130.44,
                "BarCode": "1200143202616",
                "GrossPrice": 18.22,
                "GrossTotal": 21389.55,
                "U_RRP": 0.0,
                "U_Article": null,
                "U_JumiaSKU": null,
                "U_FOC": "No",
                "UnitsOfMeasurment": 1.0
            }
        },
        {
            "PurchaseDeliveryNotes": {
                "DocEntry": 8,
                "DocNum": 1000008,
                "CreationDate": "2024-11-15",
                "CardCode": "VL-0002",
                "CardName": "Common Project Trading DMCC",
                "DocCurrency": "USD",
                "DocRate": 130.44,
                "NumAtCard": "Reebok SS24-KEN- J01",
                "Reference1": "1000008",
                "Comments": "Based On Purchase Orders 1000004.",
                "JournalMemo": "Goods Receipt PO - VL-0002"
            },
            "PurchaseDeliveryNotes/DocumentLines": {
                "ItemCode": "07/100074845/6-",
                "ItemDescription": "REEBOK COURT RETRO",
                "ShipDate": "2024-09-01",
                "Quantity": 1.0,
                "Price": 18.22,
                "PriceAfterVAT": 18.22,
                "Currency": "USD",
                "WarehouseCode": "KEN\\JU01",
                "Rate": 130.44,
                "BarCode": "1200143202623",
                "GrossPrice": 18.22,
                "GrossTotal": 2376.62,
                "U_RRP": 0.0,
                "U_Article": null,
                "U_JumiaSKU": null,
                "U_FOC": "No",
                "UnitsOfMeasurment": 1.0
            }
        },
        {
            "PurchaseDeliveryNotes": {
                "DocEntry": 8,
                "DocNum": 1000008,
                "CreationDate": "2024-11-15",
                "CardCode": "VL-0002",
                "CardName": "Common Project Trading DMCC",
                "DocCurrency": "USD",
                "DocRate": 130.44,
                "NumAtCard": "Reebok SS24-KEN- J01",
                "Reference1": "1000008",
                "Comments": "Based On Purchase Orders 1000004.",
                "JournalMemo": "Goods Receipt PO - VL-0002"
            },
            "PurchaseDeliveryNotes/DocumentLines": {
                "ItemCode": "07/100074845/6-",
                "ItemDescription": "REEBOK COURT RETRO",
                "ShipDate": "2024-09-01",
                "Quantity": 2.0,
                "Price": 18.22,
                "PriceAfterVAT": 18.22,
                "Currency": "USD",
                "WarehouseCode": "KEN\\JU01",
                "Rate": 130.44,
                "BarCode": "1200143202623",
                "GrossPrice": 18.22,
                "GrossTotal": 4753.23,
                "U_RRP": 0.0,
                "U_Article": null,
                "U_JumiaSKU": null,
                "U_FOC": "No",
                "UnitsOfMeasurment": 1.0
            }
        },
        {
            "PurchaseDeliveryNotes": {
                "DocEntry": 8,
                "DocNum": 1000008,
                "CreationDate": "2024-11-15",
                "CardCode": "VL-0002",
                "CardName": "Common Project Trading DMCC",
                "DocCurrency": "USD",
                "DocRate": 130.44,
                "NumAtCard": "Reebok SS24-KEN- J01",
                "Reference1": "1000008",
                "Comments": "Based On Purchase Orders 1000004.",
                "JournalMemo": "Goods Receipt PO - VL-0002"
            },
            "PurchaseDeliveryNotes/DocumentLines": {
                "ItemCode": "07/100074845/7",
                "ItemDescription": "REEBOK COURT RETRO",
                "ShipDate": "2024-09-01",
                "Quantity": 2.0,
                "Price": 18.22,
                "PriceAfterVAT": 18.22,
                "Currency": "USD",
                "WarehouseCode": "KEN\\JU01",
                "Rate": 130.44,
                "BarCode": "1200143202647",
                "GrossPrice": 18.22,
                "GrossTotal": 4753.23,
                "U_RRP": 0.0,
                "U_Article": null,
                "U_JumiaSKU": null,
                "U_FOC": "No",
                "UnitsOfMeasurment": 1.0
            }
        },
        {
            "PurchaseDeliveryNotes": {
                "DocEntry": 8,
                "DocNum": 1000008,
                "CreationDate": "2024-11-15",
                "CardCode": "VL-0002",
                "CardName": "Common Project Trading DMCC",
                "DocCurrency": "USD",
                "DocRate": 130.44,
                "NumAtCard": "Reebok SS24-KEN- J01",
                "Reference1": "1000008",
                "Comments": "Based On Purchase Orders 1000004.",
                "JournalMemo": "Goods Receipt PO - VL-0002"
            },
            "PurchaseDeliveryNotes/DocumentLines": {
                "ItemCode": "07/100074892/6US",
                "ItemDescription": "REEBOK LITE 4",
                "ShipDate": "2024-09-01",
                "Quantity": 3.0,
                "Price": 18.95,
                "PriceAfterVAT": 18.95,
                "Currency": "USD",
                "WarehouseCode": "KEN\\JU01",
                "Rate": 130.44,
                "BarCode": "1200143214459",
                "GrossPrice": 18.95,
                "GrossTotal": 7415.51,
                "U_RRP": 0.0,
                "U_Article": null,
                "U_JumiaSKU": null,
                "U_FOC": "No",
                "UnitsOfMeasurment": 1.0
            }
        },
        {
            "PurchaseDeliveryNotes": {
                "DocEntry": 8,
                "DocNum": 1000008,
                "CreationDate": "2024-11-15",
                "CardCode": "VL-0002",
                "CardName": "Common Project Trading DMCC",
                "DocCurrency": "USD",
                "DocRate": 130.44,
                "NumAtCard": "Reebok SS24-KEN- J01",
                "Reference1": "1000008",
                "Comments": "Based On Purchase Orders 1000004.",
                "JournalMemo": "Goods Receipt PO - VL-0002"
            },
            "PurchaseDeliveryNotes/DocumentLines": {
                "ItemCode": "07/100074892/4",
                "ItemDescription": "REEBOK LITE 4",
                "ShipDate": "2024-09-01",
                "Quantity": 6.0,
                "Price": 18.95,
                "PriceAfterVAT": 18.95,
                "Currency": "USD",
                "WarehouseCode": "KEN\\JU01",
                "Rate": 130.44,
                "BarCode": "1200143214473",
                "GrossPrice": 18.95,
                "GrossTotal": 14831.03,
                "U_RRP": 0.0,
                "U_Article": null,
                "U_JumiaSKU": null,
                "U_FOC": "No",
                "UnitsOfMeasurment": 1.0
            }
        }
    ],
    "odata.nextLink": "$crossjoin(PurchaseDeliveryNotes,PurchaseDeliveryNotes/DocumentLines)?$expand=PurchaseDeliveryNotes($select=DocEntry,DocNum,CreationDate,CardCode,CardName,DocCurrency,DocRate,NumAtCard,Reference1,Comments,JournalMemo),PurchaseDeliveryNotes/DocumentLines($select=ItemCode,ItemDescription,ShipDate,Quantity,Price,PriceAfterVAT,Currency,WarehouseCode,Rate,BarCode,GrossPrice,GrossTotal,U_RRP,U_Article,U_JumiaSKU,U_FOC,UnitsOfMeasurment)&$filter=PurchaseDeliveryNotes/DocEntry%20eq%20PurchaseDeliveryNotes/DocumentLines/DocEntry%20and%20PurchaseDeliveryNotes/CreationDate%20eq%20datetime'%202024-11-15'&$skip=300"
}